Workbook

Sheet 202507
A1: 报销形式 | B1: 公司 | C1: 审批编码 | D1: 姓名 | E1: 部门-详 | F1: 部门 | G1: 费用科目 | H1: 费用摘要 | I1: 日期 | J1: 差旅费交通 | K1: 住宿费 | L1: 文印快递 | M1: 招待费 | N1: 市内交通 | O1: 油费 | P1: 过路过桥停车费 | Q1: 团建费 | R1: 固定资产 | S1: IT建设 | T1: 福利费 | U1: 办公费 | V1: 维修费 | W1: 市场费 | X1: 会务费 | Y1: 通讯费 | Z1: 出差餐补 | AA1: 其他 | AB1: 小计 | AC1: 发票数量
A2: 一般报销 | B2: 无锡泊客 | C2: 202507211042000152066 | D2: 周肖琪 | E2: HR-HR01 | F2: HR | G2: =_xlfn.XLOOKUP(D2,[1]费用科目!A:A,[1]费用科目!C:C) -> 管理费用 | H2: 快递费 | I2: 2025-07-21 | N2: 34 | AB2: =SUM(J2:AA2) -> 34 | AC2: 1
A3: 一般报销 | B3: 无锡泊客 | C3: 202507192208000214911 | D3: 沈思 | E3: Revenue Recovery-Pido Team | F3: Revenue Recovery | G3: =VLOOKUP(D3,[1]费用科目!A:C,3,0) -> 管理费用 | H3: 加班打车 | I3: 2025-07-19 | N3: 85.68 | AB3: =SUM(J3:AA3) -> 85.68 | AC3: 4
A4: 一般报销 | B4: 无锡泊客 | C4: 202507191950000173809 | D4: 章琦 | E4: Yumin Team-Cocoa Team-DSP Team | F4: Yumin Team | G4: =VLOOKUP(D4,[1]费用科目!A:C,3,0) -> 管理费用 | H4: 加班打车 | I4: 2025-07-19 | N4: 15.22 | AB4: =SUM(J4:AA4) -> 15.22 | AC4: 1
A5: 一般报销 | B5: 无锡泊客 | C5: 202507211528000439864 | D5: 袁丽娟 | E5: HR-HR01 | F5: HR | G5: =VLOOKUP(D5,[1]费用科目!A:C,3,0) -> 管理费用 | H5: 快递费&市内交通&软件费 | I5: 2025-07-21 | L5: 233.9 | N5: 58.1 | S5: 3500 | AB5: =SUM(J5:AA5) -> 3792 | AC5: 4
A6: 一般报销 | B6: 无锡泊客 | C6: 202507211303000360816 | D6: 赵凤新 | E6: PM&UED-PM | F6: PM&UED | G6: =VLOOKUP(D6,[1]费用科目!A:C,3,0) -> 研发费用 | H6: 签证费 | I6: 2025-07-21 | AA6: 3500 | AB6: =SUM(J6:AA6) -> 3500 | AC6: 1
A7: 一般报销 | B7: 无锡泊客 | C7: 202507211559000024466 | D7: 马晴 | E7: Revenue Recovery | F7: Revenue Recovery | G7: =VLOOKUP(D7,[1]费用科目!A:C,3,0) -> 管理费用 | H7: 加班打车 | I7: 2025-07-21 | N7: 96 | AB7: =SUM(J7:AA7) -> 96 | AC7: 12
A8: 一般报销 | B8: 无锡泊客 | C8: 202507181812000450754 | D8: 宋薇 | E8: Yumin Team-H10_SZ | F8: Yumin Team | G8: =VLOOKUP(D8,[1]费用科目!A:C,3,0) -> 管理费用 | H8: 7月15日杭州闭门会中午购买43张30元午餐餐券，以及三箱活动用水 | I8: 2025-07-18 | W8: 1434 | AB8: =SUM(J8:AA8) -> 1434 | AC8: 1
A9: 一般报销 | B9: 无锡泊客 | C9: 202507181436000461811 | D9: 顾雯雯 | E9: HR-HR01 | F9: HR | G9: =VLOOKUP(D9,[1]费用科目!A:C,3,0) -> 管理费用 | H9: 招聘费用 | I9: 2025-07-18 | N9: 30.71 | U9: 78 | AB9: =SUM(J9:AA9) -> 108.71 | AC9: 2
A10: 一般报销 | B10: 无锡泊客 | C10: 202507181412000175704 | D10: 李胤楼 | E10: HR-HR01 | F10: HR | G10: =VLOOKUP(D10,[1]费用科目!A:C,3,0) -> 管理费用 | H10: 办公费&福利费&快递费 | I10: 2025-07-18 | L10: 12 | T10: 3031.12 | U10: 4706.39 | AB10: =SUM(J10:AA10) -> 7749.51 | AC10: 11
A11: 一般报销 | B11: 无锡泊客 | C11: 202507181032000161813 | D11: 马章瑜 | E11: R&D-SMB | F11: R&D | G11: =VLOOKUP(D11,[1]费用科目!A:C,3,0) -> 研发费用 | H11: 团建费 | I11: 2025-07-18 | Q11: 6378.95 | AB11: =SUM(J11:AA11) -> 6378.95 | AC11: 11
A12: 一般报销 | B12: 无锡泊客 | C12: 202507180931000237464 | D12: 皇甫苗苗 | E12: R&D-QA&PMO-QA-Test-Commerce Test Team | F12: R&D | G12: =VLOOKUP(D12,[1]费用科目!A:C,3,0) -> 研发费用 | H12: 加班打车 | I12: 2025-07-18 | N12: 111.72 | AB12: =SUM(J12:AA12) -> 111.72 | AC12: 8
A13: 一般报销 | B13: 无锡泊客 | C13: 202507172207000168100 | D13: 李璐 | E13: R&D-QA&PMO-QA-Test-Helium 10 Test Team | F13: R&D | G13: =VLOOKUP(D13,[1]费用科目!A:C,3,0) -> 研发费用 | H13: 加班打车 | I13: 2025-07-17 | N13: 45.4 | AB13: =SUM(J13:AA13) -> 45.4 | AC13: 1
A14: 一般报销 | B14: 无锡泊客 | C14: 202507171810000106051 | D14: 吉羽 | E14: R&D-Enterprise-Corporate IT | F14: R&D | G14: =VLOOKUP(D14,[1]费用科目!A:C,3,0) -> 研发费用 | H14: 快递费 | I14: 2025-07-17 | L14: 127 | AB14: =SUM(J14:AA14) -> 127 | AC14: 1
A15: 一般报销 | B15: 无锡泊客 | C15: 202507171350000515422 | D15: 殷子心 | E15: R&D-Enterprise | F15: R&D | G15: =VLOOKUP(D15,[1]费用科目!A:C,3,0) -> 研发费用 | H15: 团建费 | I15: 2025-07-17 | Q15: 7101.35 | S15: 2982.03 | AB15: =SUM(J15:AA15) -> 10083.38 | AC15: 9
A16: 一般报销 | B16: 无锡泊客 | C16: 202507170851000339693 | D16: 管燕山 | E16: R&D-Enterprise-Commerce-Front End | F16: R&D | G16: =VLOOKUP(D16,[1]费用科目!A:C,3,0) -> 研发费用 | H16: 加班打车 | I16: 2025-07-17 | N16: 75.8 | AB16: =SUM(J16:AA16) -> 75.8 | AC16: 2
A17: 一般报销 | B17: 无锡泊客 | C17: 202507161335000493772 | D17: 蔡佳菡 | E17: HR-HR01 | F17: HR | G17: =VLOOKUP(D17,[1]费用科目!A:C,3,0) -> 管理费用 | H17: 办公费&福利费 | I17: 2025-07-16 | T17: 3179.37 | U17: 296.21 | AB17: =SUM(J17:AA17) -> 3475.58 | AC17: 15
A18: 一般报销 | B18: 无锡泊客 | C18: 202507161108000216812 | D18: 李凯 | E18: PM&UED-UED Enterprise | F18: PM&UED | G18: =VLOOKUP(D18,[1]费用科目!A:C,3,0) -> 研发费用 | H18: 差旅费 | I18: 2025-07-16 | J18: 106 | AB18: =SUM(J18:AA18) -> 106 | AC18: 2
A19: 一般报销 | B19: 无锡泊客 | C19: 202507161010000118303 | D19: 方玲 | E19: R&D-QA&PMO-QA-Test-Middle Platform Test Team | F19: R&D | G19: =VLOOKUP(D19,[1]费用科目!A:C,3,0) -> 研发费用 | H19: 加班打车 | I19: 2025-07-16 | N19: 145 | AB19: =SUM(J19:AA19) -> 145 | AC19: 2
A20: 一般报销 | B20: 无锡泊客 | C20: 202507160954000380059 | D20: 葛成杰 | E20: R&D-Enterprise-Commerce-Front End | F20: R&D | G20: =VLOOKUP(D20,[1]费用科目!A:C,3,0) -> 研发费用 | H20: 加班打车 | I20: 2025-07-16 | N20: 43.46 | AB20: =SUM(J20:AA20) -> 43.46 | AC20: 1
A21: 一般报销 | B21: 无锡泊客 | C21: 202507160950000185179 | D21: 李振强 | E21: R&D-Enterprise-Commerce-Front End | F21: R&D | G21: =VLOOKUP(D21,[1]费用科目!A:C,3,0) -> 研发费用 | H21: 加班打车 | I21: 2025-07-16 | N21: 346.6 | AB21: =SUM(J21:AA21) -> 346.6 | AC21: 1
A22: 一般报销 | B22: 无锡泊客 | C22: 202507160940000564273 | D22: 梅宝文 | E22: R&D-QA&PMO-QA-Test-Commerce Test Team | F22: R&D | G22: =VLOOKUP(D22,[1]费用科目!A:C,3,0) -> 研发费用 | H22: 加班打车 | I22: 2025-07-16 | N22: 35.05 | AB22: =SUM(J22:AA22) -> 35.05 | AC22: 3
A23: 一般报销 | B23: 无锡泊客 | C23: 202507160935000249026 | D23: 陈雨 | E23: R&D-Enterprise-Commerce-Content Management | F23: R&D | G23: =VLOOKUP(D23,[1]费用科目!A:C,3,0) -> 研发费用 | H23: 加班打车 | I23: 2025-07-16 | N23: 56.08 | AB23: =SUM(J23:AA23) -> 56.08 | AC23: 1
A24: 一般报销 | B24: 无锡泊客 | C24: 202507101013000457377 | D24: 刘瑞敏 | E24: R&D-QA&PMO-QA-Test-Helium 10 Test Team | F24: R&D | G24: =VLOOKUP(D24,[1]费用科目!A:C,3,0) -> 研发费用 | H24: 加班打车 | I24: 2025-07-10 | N24: 50.83 | AB24: =SUM(J24:AA24) -> 50.83 | AC24: 1
A25: 一般报销 | B25: 无锡泊客 | C25: 202507091435000573640 | D25: 高晓晨 | E25: Yumin Team-Cocoa Team-CS Team | F25: Yumin Team | G25: =VLOOKUP(D25,[1]费用科目!A:C,3,0) -> 管理费用 | H25: 差旅费 | I25: 2025-07-09 | J25: 424 | N25: 73.76 | AB25: =SUM(J25:AA25) -> 497.76 | AC25: 5
A26: 一般报销 | B26: 无锡泊客 | C26: 202507091037000361675 | D26: 魏宁玲 | E26: Yumin Team-Cocoa Team-CS Team | F26: Yumin Team | G26: =VLOOKUP(D26,[1]费用科目!A:C,3,0) -> 管理费用 | H26: 差旅费 | I26: 2025-07-09 | J26: 424 | N26: 27.71 | AB26: =SUM(J26:AA26) -> 451.71 | AC26: 3
A27: 一般报销 | B27: 无锡泊客 | C27: 202507081213000517920 | D27: 丁力 | E27: R&D-Enterprise-Commerce | F27: R&D | G27: =VLOOKUP(D27,[1]费用科目!A:C,3,0) -> 研发费用 | H27: 面签&快递费&签证费 | I27: 2025-07-08 | J27: 538 | K27: 119.75 | L27: 110 | AA27: 1368 | AB27: =SUM(J27:AA27) -> 2135.75 | AC27: 5
A28: 一般报销 | B28: 无锡泊客 | C28: 202507071439000161192 | D28: 姬礼 | E28: R&D-QA&PMO-QA-Test-Middle Platform Test Team | F28: R&D | G28: =VLOOKUP(D28,[1]费用科目!A:C,3,0) -> 研发费用 | H28: 加班打车 | I28: 2025-07-07 | N28: 30 | AB28: =SUM(J28:AA28) -> 30 | AC28: 1
A29: 一般报销 | B29: 无锡泊客 | C29: 202507071203000291523 | D29: 张安谊 | E29: R&D-Enterprise-Corporate IT | F29: R&D | G29: =VLOOKUP(D29,[1]费用科目!A:C,3,0) -> 研发费用 | H29: 团建费 | I29: 2025-07-07 | Q29: 1102 | AB29: =SUM(J29:AA29) -> 1102 | AC29: 1
A30: 一般报销 | B30: 无锡泊客 | C30: 202507040959000114870 | D30: 李璐 | E30: R&D-QA&PMO-QA-Test-Helium 10 Test Team | F30: R&D | G30: =VLOOKUP(D30,[1]费用科目!A:C,3,0) -> 研发费用 | H30: 加班打车 | I30: 2025-07-04 | Q30: 212.7 | AB30: =SUM(J30:AA30) -> 212.7 | AC30: 1
A31: 一般报销 | B31: 无锡泊客 | C31: 202507011047000578303 | D31: 马章瑜 | E31: R&D-SMB | F31: R&D | G31: =VLOOKUP(D31,[1]费用科目!A:C,3,0) -> 研发费用 | H31: 团建费 | I31: 2025-07-01 | Q31: 845.97 | AB31: =SUM(J31:AA31) -> 845.97 | AC31: 2
A32: 一般报销 | B32: 无锡泊客 | C32: 202506302054000237319 | D32: 费冬梅 | E32: Yumin Team-Cocoa Team-DSP Team | F32: Yumin Team | G32: =VLOOKUP(D32,[1]费用科目!A:C,3,0) -> 管理费用 | H32: 加班打车 | I32: 2025-06-30 | N32: 130.3 | AB32: =SUM(J32:AA32) -> 130.3 | AC32: 1
A33: 一般报销 | B33: 无锡泊客 | C33: 202506271213000003160 | D33: 周盼盼 | E33: R&D-QA&PMO-QA-Test-Commerce Test Team | F33: R&D | G33: =VLOOKUP(D33,[1]费用科目!A:C,3,0) -> 研发费用 | H33: 加班打车 | I33: 2025-06-27 | N33: 33.13 | AB33: =SUM(J33:AA33) -> 33.13 | AC33: 1
A34: 一般报销 | B34: 无锡泊客 | C34: 202506271208000562306 | D34: 周盼盼 | E34: R&D-QA&PMO-QA-Test-Commerce Test Team | F34: R&D | G34: =VLOOKUP(D34,[1]费用科目!A:C,3,0) -> 研发费用 | H34: 加班打车 | I34: 2025-06-27 | N34: 178.3 | AB34: =SUM(J34:AA34) -> 178.3 | AC34: 1
A35: 一般报销 | B35: 无锡泊客 | C35: 202506241615000421229 | D35: 江正贯 | E35: R&D-Enterprise-Data ETL | F35: R&D | G35: =VLOOKUP(D35,[1]费用科目!A:C,3,0) -> 研发费用 | H35: 软件服务费 | I35: 2025-06-24 | S35: 2028 | AB35: =SUM(J35:AA35) -> 2028 | AC35: 1
A36: 一般报销 | B36: 无锡泊客 | C36: 202507171708000235667 | D36: 王宇锋 | E36: R&D-SMB-Offline Data Processing-Data Acquisition | F36: R&D | G36: =VLOOKUP(D36,[1]费用科目!A:C,3,0) -> 研发费用 | H36: CN IP 代理 | I36: 2025-07-17 | S36: 7160 | AB36: =SUM(J36:AA36) -> 7160 | AC36: 1
A37: 一般报销 | B37: 无锡泊客 | C37: 202507181425000591672 | D37: 张云云 | E37: HR-HR01 | F37: HR | G37: =VLOOKUP(D37,[1]费用科目!A:C,3,0) -> 管理费用 | H37: 快递费 | I37: 2025-07-18 | N37: 126.24 | AB37: =SUM(J37:AA37) -> 126.24 | AC37: 2
A38: 差旅费报销 | B38: 无锡泊客 | C38: 202507211633000265858 | D38: 殷子心 | E38: R&D | F38: R&D | G38: =VLOOKUP(D38,[1]费用科目!A:C,3,0) -> 研发费用 | H38: 出差1天 | I38: 2025-07-21 | J38: 126 | N38: 84.2 | AB38: =SUM(J38:AA38) -> 210.2 | AC38: 4
A39: 差旅费报销 | B39: 无锡泊客 | C39: 202507181921000193069 | D39: 马晴 | E39: Revenue Recovery | F39: Revenue Recovery | G39: =VLOOKUP(D39,[1]费用科目!A:C,3,0) -> 管理费用 | H39: 出差1天 | I39: 2025-07-18 | N39: 90.09 | AB39: =SUM(J39:AA39) -> 90.09 | AC39: 2
A40: 差旅费报销 | B40: 无锡泊客 | C40: 202507192219000356946 | D40: 沈思 | E40: Revenue Recovery-Pido Team | F40: Revenue Recovery | G40: =VLOOKUP(D40,[1]费用科目!A:C,3,0) -> 管理费用 | H40: 出差3天 | I40: 2025-07-19 | N40: 403.05 | AB40: =SUM(J40:AA40) -> 403.05 | AC40: 5
A41: 差旅费报销 | B41: 无锡泊客 | C41: 202507191945000483789 | D41: 章琦 | E41: Yumin Team-Cocoa Team-DSP Team | F41: Yumin Team | G41: =VLOOKUP(D41,[1]费用科目!A:C,3,0) -> 管理费用 | H41: 出差3天 | I41: 2025-07-19 | J41: 3656 | K41: 1289.04 | N41: 132.73 | AB41: =SUM(J41:AA41) -> 5077.77 | AC41: 9
A42: 差旅费报销 | B42: 无锡泊客 | C42: 202507181605000420856 | D42: 史立丽 | E42: PM&UED-PM-SMB Ads | F42: PM&UED | G42: =VLOOKUP(D42,[1]费用科目!A:C,3,0) -> 研发费用 | H42: 出差2天 | I42: 2025-07-18 | K42: 359.56 | N42: 58.59 | AB42: =SUM(J42:AA42) -> 418.15 | AC42: 4
A43: 差旅费报销 | B43: 无锡泊客 | C43: 202507181831000188638 | D43: 马晴 | E43: Revenue Recovery | F43: Revenue Recovery | G43: =VLOOKUP(D43,[1]费用科目!A:C,3,0) -> 管理费用 | H43: 出差1天 | I43: 2025-07-18 | N43: 135 | AB43: =SUM(J43:AA43) -> 135 | AC43: 2
A44: 差旅费报销 | B44: 无锡泊客 | C44: 202507181828000597411 | D44: 马晴 | E44: Revenue Recovery | F44: Revenue Recovery | G44: =VLOOKUP(D44,[1]费用科目!A:C,3,0) -> 管理费用 | H44: 出差1天 | I44: 2025-07-18 | N44: 241 | AB44: =SUM(J44:AA44) -> 241 | AC44: 2
A45: 差旅费报销 | B45: 无锡泊客 | C45: 202507181827000331065 | D45: 刘晶鑫 | E45: PM&UED-UED Helium 10 | F45: PM&UED | G45: =VLOOKUP(D45,[1]费用科目!A:C,3,0) -> 研发费用 | H45: 出差2天 | I45: 2025-07-18 | J45: 274 | K45: 666 | AB45: =SUM(J45:AA45) -> 940 | AC45: 5
A46: 差旅费报销 | B46: 无锡泊客 | C46: 202507181827000153924 | D46: 马晴 | E46: Revenue Recovery | F46: Revenue Recovery | G46: =VLOOKUP(D46,[1]费用科目!A:C,3,0) -> 管理费用 | H46: 出差1天 | I46: 2025-07-18 | N46: 131.14 | AB46: =SUM(J46:AA46) -> 131.14 | AC46: 2
A47: 差旅费报销 | B47: 无锡泊客 | C47: 202507181824000124879 | D47: 马晴 | E47: Revenue Recovery | F47: Revenue Recovery | G47: =VLOOKUP(D47,[1]费用科目!A:C,3,0) -> 管理费用 | H47: 出差1天 | I47: 2025-07-18 | N47: 96.4 | AB47: =SUM(J47:AA47) -> 96.4 | AC47: 2
A48: 差旅费报销 | B48: 无锡泊客 | C48: 202507181657000574045 | D48: 龚伟 | E48: PM&UED-DS Team | F48: PM&UED | G48: =VLOOKUP(D48,[1]费用科目!A:C,3,0) -> 研发费用 | H48: 出差3天 | I48: 2025-07-18 | J48: 313 | AB48: =SUM(J48:AA48) -> 313 | AC48: 5
A49: 差旅费报销 | B49: 无锡泊客 | C49: 202507181326000530754 | D49: 宋薇 | E49: Yumin Team-H10_SZ | F49: Yumin Team | G49: =VLOOKUP(D49,[1]费用科目!A:C,3,0) -> 管理费用 | H49: 出差3天 | I49: 2025-07-18 | J49: 274 | K49: 684 | N49: 200.13 | AB49: =SUM(J49:AA49) -> 1158.13 | AC49: 9
A50: 差旅费报销 | B50: 无锡泊客 | C50: 202507172203000027051 | D50: 李璐 | E50: R&D-QA&PMO-QA-Test-Helium 10 Test Team | F50: R&D | G50: =VLOOKUP(D50,[1]费用科目!A:C,3,0) -> 研发费用 | H50: 出差1天 | I50: 2025-07-17 | N50: 177.1 | AB50: =SUM(J50:AA50) -> 177.1 | AC50: 1
A51: 差旅费报销 | B51: 无锡泊客 | C51: 202507172131000150857 | D51: 费冬梅 | E51: Yumin Team-Cocoa Team-DSP Team | F51: Yumin Team | G51: =VLOOKUP(D51,[1]费用科目!A:C,3,0) -> 管理费用 | H51: 出差3天 | I51: 2025-07-17 | J51: 31 | K51: 689.64 | N51: 274.81 | AB51: =SUM(J51:AA51) -> 995.45 | AC51: 4
A52: 差旅费报销 | B52: 无锡泊客 | C52: 202507172129000099812 | D52: 胡东明 | E52: R&D-SMB-Online services Engineering-Research Tools Team | F52: R&D | G52: =VLOOKUP(D52,[1]费用科目!A:C,3,0) -> 研发费用 | H52: 出差1天 | I52: 2025-07-17 | J52: 52 | N52: 92.42 | AB52: =SUM(J52:AA52) -> 144.42 | AC52: 5
A53: 差旅费报销 | B53: 无锡泊客 | C53: 202507171808000429842 | D53: 马晴 | E53: Revenue Recovery | F53: Revenue Recovery | G53: =VLOOKUP(D53,[1]费用科目!A:C,3,0) -> 管理费用 | H53: 出差1天 | I53: 2025-07-17 | J53: 228 | N53: 57.54 | AB53: =SUM(J53:AA53) -> 285.54 | AC53: 4
A54: 差旅费报销 | B54: 无锡泊客 | C54: 202507171549000344073 | D54: 吉羽 | E54: R&D-Enterprise-Corporate IT | F54: R&D | G54: =VLOOKUP(D54,[1]费用科目!A:C,3,0) -> 研发费用 | H54: 出差1天 | I54: 2025-07-17 | N54: 219.29 | AB54: =SUM(J54:AA54) -> 219.29 | AC54: 4
A55: 差旅费报销 | B55: 无锡泊客 | C55: 202507171501000102906 | D55: 马章瑜 | E55: R&D-SMB | F55: R&D | G55: =VLOOKUP(D55,[1]费用科目!A:C,3,0) -> 研发费用 | H55: 出差4天 | I55: 2025-07-17 | K55: 1050 | N55: 183.82 | AB55: =SUM(J55:AA55) -> 1233.82 | AC55: 2
A56: 差旅费报销 | B56: 无锡泊客 | C56: 202507171407000593037 | D56: 韩苏闻 | E56: R&D-SMB-Architecture-Optimization | F56: R&D | G56: =VLOOKUP(D56,[1]费用科目!A:C,3,0) -> 研发费用 | H56: 出差2天 | I56: 2025-07-17 | J56: 84 | AB56: =SUM(J56:AA56) -> 84 | AC56: 4
A57: 差旅费报销 | B57: 无锡泊客 | C57: 202507171347000383046 | D57: 吕溢 | E57: R&D-SMB-Architecture-Optimization | F57: R&D | G57: =VLOOKUP(D57,[1]费用科目!A:C,3,0) -> 研发费用 | H57: 出差1天 | I57: 2025-07-17 | N57: 169 | AB57: =SUM(J57:AA57) -> 169 | AC57: 2
A58: 差旅费报销 | B58: 无锡泊客 | C58: 202507171201000144577 | D58: 陈晓林 | E58: PM&UED-PM-SMB Ads | F58: PM&UED | G58: =VLOOKUP(D58,[1]费用科目!A:C,3,0) -> 研发费用 | H58: 出差1天 | I58: 2025-07-17 | J58: 262 | N58: 129.24 | AB58: =SUM(J58:AA58) -> 391.24 | AC58: 5
A59: 差旅费报销 | B59: 无锡泊客 | C59: 202507170913000033046 | D59: 陈玲 | E59: PM&UED-UED Enterprise | F59: PM&UED | G59: =VLOOKUP(D59,[1]费用科目!A:C,3,0) -> 研发费用 | H59: 出差1天 | I59: 2025-07-17 | N59: 234 | AB59: =SUM(J59:AA59) -> 234 | AC59: 1
A60: 差旅费报销 | B60: 无锡泊客 | C60: 202507161320000459097 | D60: 陈琛 | E60: PM&UED-PM-Commerce | F60: PM&UED | G60: =VLOOKUP(D60,[1]费用科目!A:C,3,0) -> 研发费用 | H60: 出差1天 | I60: 2025-07-16 | N60: 212.1 | AB60: =SUM(J60:AA60) -> 212.1 | AC60: 1
A61: 差旅费报销 | B61: 无锡泊客 | C61: 202507160942000491411 | D61: 李振强 | E61: R&D-Enterprise-Commerce-Front End | F61: R&D | G61: =VLOOKUP(D61,[1]费用科目!A:C,3,0) -> 研发费用 | H61: 出差1天 | I61: 2025-07-16 | N61: 152.4 | AB61: =SUM(J61:AA61) -> 152.4 | AC61: 1
A62: 差旅费报销 | B62: 无锡泊客 | C62: 202507151232000410360 | D62: 张帅涛 | E62: R&D-Enterprise-Commerce-RRM | F62: R&D | G62: =VLOOKUP(D62,[1]费用科目!A:C,3,0) -> 研发费用 | H62: 出差1天 | I62: 2025-07-15 | N62: 213.6 | AB62: =SUM(J62:AA62) -> 213.6 | AC62: 2
A63: 差旅费报销 | B63: 无锡泊客 | C63: 202507131821000074633 | D63: 秦铮铮 | E63: Yumin Team-Cocoa Team-DSP Team | F63: Yumin Team | G63: =VLOOKUP(D63,[1]费用科目!A:C,3,0) -> 管理费用 | H63: 出差3天 | I63: 2025-07-13 | J63: 2137 | K63: 431 | N63: 84.81 | AB63: =SUM(J63:AA63) -> 2652.81 | AC63: 6
A64: 差旅费报销 | B64: 无锡泊客 | C64: 202507111434000241712 | D64: 金一泽 | E64: R&D-SMB-Online services Engineering-Ads&Commerce Team | F64: R&D | G64: =VLOOKUP(D64,[1]费用科目!A:C,3,0) -> 研发费用 | H64: 出差1天 | I64: 2025-07-11 | P64: 42 | AB64: =SUM(J64:AA64) -> 42 | AC64: 9
A65: 差旅费报销 | B65: 无锡泊客 | C65: 202507091734000200770 | D65: 高晓晨 | E65: Yumin Team-Cocoa Team-CS Team | F65: Yumin Team | G65: =VLOOKUP(D65,[1]费用科目!A:C,3,0) -> 管理费用 | H65: 出差4天 | I65: 2025-07-09 | J65: 2125 | K65: 1127 | N65: 71.67 | AB65: =SUM(J65:AA65) -> 3323.67 | AC65: 8
A66: 差旅费报销 | B66: 无锡泊客 | C66: 202507071808000087927 | D66: 夏寅海 | E66: R&D-SMB-DevOps | F66: R&D | G66: =VLOOKUP(D66,[1]费用科目!A:C,3,0) -> 研发费用 | H66: 出差2天 | I66: 2025-07-07 | J66: 88 | K66: 433.88 | AB66: =SUM(J66:AA66) -> 521.88 | AC66: 3
A67: 差旅费报销 | B67: 无锡泊客 | C67: 202507071037000019686 | D67: 张安谊 | E67: R&D-Enterprise-Corporate IT | F67: R&D | G67: =VLOOKUP(D67,[1]费用科目!A:C,3,0) -> 研发费用 | H67: 出差5天 | I67: 2025-07-07 | J67: 361 | N67: 194.13 | P67: 77 | AB67: =SUM(J67:AA67) -> 632.13 | AC67: 28
A68: 差旅费报销 | B68: 无锡泊客 | C68: 202507061757000264757 | D68: 秦旺进 | E68: R&D-SMB-Online services Engineering-Research Tools Team-Shared Service | F68: R&D | G68: =VLOOKUP(D68,[1]费用科目!A:C,3,0) -> 研发费用 | H68: 出差4天 | I68: 2025-07-06 | J68: 130 | K68: 733.88 | AB68: =SUM(J68:AA68) -> 863.88 | AC68: 6
A69: 差旅费报销 | B69: 无锡泊客 | C69: 202507161317000400780 | D69: 陈琛 | E69: PM&UED-PM-Commerce | F69: PM&UED | G69: =VLOOKUP(D69,[1]费用科目!A:C,3,0) -> 研发费用 | H69: 出差1天 | I69: 2025-07-16 | N69: 231.78 | AB69: =SUM(J69:AA69) -> 231.78 | AC69: 1
A70: 差旅费报销 | B70: 无锡泊客 | C70: 202507041017000039961 | D70: 李璐 | E70: R&D-QA&PMO-QA-Test-Helium 10 Test Team | F70: R&D | G70: =VLOOKUP(D70,[1]费用科目!A:C,3,0) -> 研发费用 | H70: 出差2天 | I70: 2025-07-04 | J70: 171 | AB70: =SUM(J70:AA70) -> 171 | AC70: 4
A71: 差旅费报销 | B71: 无锡泊客 | C71: 202507031644000183138 | D71: 姜智明 | E71: PM&UED-PM-Data and AI | F71: PM&UED | G71: =VLOOKUP(D71,[1]费用科目!A:C,3,0) -> 研发费用 | H71: 出差1天 | I71: 2025-07-03 | J71: 49 | AB71: =SUM(J71:AA71) -> 49 | AC71: 1
A72: 差旅费报销 | B72: 无锡泊客 | C72: 202507021716000496530 | D72: 吉羽 | E72: R&D-Enterprise-Corporate IT | F72: R&D | G72: =VLOOKUP(D72,[1]费用科目!A:C,3,0) -> 研发费用 | H72: 出差1天 | I72: 2025-07-02 | N72: 186.55 | P72: 22 | AB72: =SUM(J72:AA72) -> 208.55 | AC72: 4
A73: 差旅费报销 | B73: 无锡泊客 | C73: 202507031631000321280 | D73: 姜智明 | E73: PM&UED-PM-Data and AI | F73: PM&UED | G73: =VLOOKUP(D73,[1]费用科目!A:C,3,0) -> 研发费用 | H73: 出差1天 | I73: 2025-07-03 | J73: 65 | AB73: =SUM(J73:AA73) -> 65 | AC73: 2
A74: 差旅费报销 | B74: 无锡泊客 | C74: 202506160135000091796 | D74: 王恩平 | E74: Yumin Team-Cocoa Team | F74: Yumin Team | G74: =VLOOKUP(D74,[1]费用科目!A:C,3,0) -> 管理费用 | H74: 出差26天 | I74: 2025-06-16 | J74: 8146.5 | K74: 5001.3 | N74: 2494.03 | P74: 26 | AB74: =SUM(J74:AA74) -> 15667.83 | AC74: 30
A75: 差旅费报销 | B75: 无锡泊客 | C75: 202507012221000439813 | D75: 秦铮铮 | E75: Yumin Team-Cocoa Team-DSP Team | F75: Yumin Team | G75: =VLOOKUP(D75,[1]费用科目!A:C,3,0) -> 管理费用 | H75: 出差6天 | I75: 2025-07-01 | J75: 1231.5 | K75: 573 | N75: 39.1 | AB75: =SUM(J75:AA75) -> 1843.6 | AC75: 8
A76: 差旅费报销 | B76: 无锡泊客 | C76: 202507011559000578297 | D76: 马章瑜 | E76: R&D-SMB | F76: R&D | G76: =VLOOKUP(D76,[1]费用科目!A:C,3,0) -> 研发费用 | H76: 出差8天 | I76: 2025-07-01 | J76: 19551 | K76: 5490.41 | N76: 1542.88 | AA76: 494.96 | AB76: =SUM(J76:AA76) -> 27079.25 | AC76: 14
A77: 差旅费报销 | B77: 无锡泊客 | C77: 202506300934000466629 | D77: 马章瑜 | E77: R&D-SMB | F77: R&D | G77: =VLOOKUP(D77,[1]费用科目!A:C,3,0) -> 研发费用 | H77: 出差2天 | I77: 2025-06-30 | J77: 167 | K77: 450 | N77: 231.4 | AB77: =SUM(J77:AA77) -> 848.4 | AC77: 7
A78: 差旅费报销 | B78: 无锡泊客 | C78: 202506160037000504897 | D78: 王恩平 | E78: Yumin Team-Cocoa Team | F78: Yumin Team | G78: =VLOOKUP(D78,[1]费用科目!A:C,3,0) -> 管理费用 | H78: 出差17天 | I78: 2025-06-16 | J78: 5283 | K78: 3457 | N78: 1870.16 | P78: 55 | AB78: =SUM(J78:AA78) -> 10665.16 | AC78: 28
A79: 差旅费报销 | B79: 无锡泊客 | C79: 202507021658000047712 | D79: 蔡鹏 | E79: R&D-SMB-Architecture-Price&Packaging | F79: R&D | G79: =VLOOKUP(D79,[1]费用科目!A:C,3,0) -> 研发费用 | H79: 出差5天 | I79: 2025-07-02 | J79: 53 | K79: 444.15 | N79: 44.37 | P79: 148.32 | AB79: =SUM(J79:AA79) -> 689.84 | AC79: 12
A80: 差旅费报销 | B80: 无锡泊客 | C80: 202507031637000337699 | D80: 姜智明 | E80: PM&UED-PM-Data and AI | F80: PM&UED | G80: =VLOOKUP(D80,[1]费用科目!A:C,3,0) -> 研发费用 | H80: 出差1天 | I80: 2025-07-03 | N80: 75 | AB80: =SUM(J80:AA80) -> 75 | AC80: 3
A81: 常规团建费报销 | B81: 无锡泊客 | C81: 202507221540000127872 | D81: 马晴 | E81: Revenue Recovery | F81: Revenue Recovery | G81: =VLOOKUP(D81,[1]费用科目!A:C,3,0) -> 管理费用 | H81: 常规团建 | I81: 2025-07-22 | Q81: 1374.9 | AB81: =SUM(J81:AA81) -> 1374.9 | AC81: 4
A82: 常规团建费报销 | B82: 无锡泊客 | C82: 202507071208000110963 | D82: 张安谊 | E82: R&D-Enterprise-Corporate IT | F82: R&D | G82: =VLOOKUP(D82,[1]费用科目!A:C,3,0) -> 研发费用 | H82: 常规团建 | I82: 2025-07-07 | Q82: 356.8 | AB82: =SUM(J82:AA82) -> 356.8 | AC82: 1
A83: 常规团建费报销 | B83: 无锡泊客 | C83: 202507071043000233822 | D83: 蔡鹏 | E83: R&D-SMB-Architecture-Price&Packaging | F83: R&D | G83: =VLOOKUP(D83,[1]费用科目!A:C,3,0) -> 研发费用 | H83: 常规团建 | I83: 2025-07-07 | Q83: 2175 | AB83: =SUM(J83:AA83) -> 2175 | AC83: 1
A84: 常规团建费报销 | B84: 无锡泊客 | C84: 202507031914000115701 | D84: 杨艳艳 | E84: PM&UED-PM-Commerce | F84: PM&UED | G84: =VLOOKUP(D84,[1]费用科目!A:C,3,0) -> 研发费用 | H84: 常规团建 | I84: 2025-07-03 | Q84: 1590 | AB84: =SUM(J84:AA84) -> 1590 | AC84: 7
A85: 常规团建费报销 | B85: 无锡泊客 | C85: 202507031511000251775 | D85: 李亚奇 | E85: R&D-Enterprise-Ads Division-Platform Dept-Amazon DSP | F85: R&D | G85: =VLOOKUP(D85,[1]费用科目!A:C,3,0) -> 研发费用 | H85: 常规团建 | I85: 2025-07-03 | Q85: 1093 | AB85: =SUM(J85:AA85) -> 1093 | AC85: 1
A86: 常规团建费报销 | B86: 无锡泊客 | C86: 202507021230000174152 | D86: 颜园园 | E86: R&D-Enterprise-Ads Division-Platform Dept-Wal & IC | F86: R&D | G86: =VLOOKUP(D86,[1]费用科目!A:C,3,0) -> 研发费用 | H86: 常规团建 | I86: 2025-07-02 | Q86: 1676 | AB86: =SUM(J86:AA86) -> 1676 | AC86: 1
A87: 常规团建费报销 | B87: 无锡泊客 | C87: 202507241448000274005 | D87: 何锐 | E87: Support & CSM | F87: Support & CSM | G87: =VLOOKUP(D87,[1]费用科目!A:C,3,0) -> 管理费用 | H87: 常规团建 | I87: 2025-07-24 | Q87: 2720.22 | AB87: =SUM(J87:AA87) -> 2720.22 | AC87: 5
